hydbedscraper/__init__.py
hydbedscraper/city.py
hydbedscraper/main.py
hydbedscraper/types.py
hydbedscraper/writer.py
hydbedscraper/drivers/__init__.py
hydbedscraper/drivers/ahmedabad.py
hydbedscraper/drivers/hyderabad.py
hydbedscraper/drivers/pune.py
hydbedscraper/drivers/vadodara.py
hydbedscraper/parsers/__init__.py
hydbedscraper/parsers/ahmedabad.py
hydbedscraper/parsers/hyderabad.py
hydbedscraper/parsers/pune.py
hydbedscraper/parsers/vadodara.py
hydbedscraper/parsers/helpers/__init__.py
hydbedscraper/parsers/helpers/cleaners.py
hydbedscraper/parsers/helpers/labels.py
hydbedscraper/requesters/__init__.py
hydbedscraper/requesters/_common.py
hydbedscraper/requesters/ahmedabad.py
hydbedscraper/requesters/hyderabad.py
hydbedscraper/requesters/pune.py
hydbedscraper/requesters/vadodara.py
hydbedscraper/writers/__init__.py
hydbedscraper/writers/vadodara.py
hydbedscraper-0.1.1.dist-info/LICENSE
hydbedscraper-0.1.1.dist-info/METADATA
hydbedscraper-0.1.1.dist-info/WHEEL
hydbedscraper-0.1.1.dist-info/top_level.txt
hydbedscraper-0.1.1.dist-info/RECORD
